<?xml version="1.0" encoding="UTF-8" standalone="no"?>
<substratum>
    <theme id="//substweaks//">
        <author>Harsh Shandilya</author>
        <link>https://play.google.com/store/apps/details?id=me.msfjarvis.substweaks</link>
        <package>me.msfjarvis.substweaks</package>
        <pricing>Free</pricing>
        <support>overlays</support>
        <backgroundimage>https://raw.githubusercontent.com/substratum/database/master/images/substweaks.png</backgroundimage>
        <image>https://lh3.googleusercontent.com/MKqm5lHSOwNfxf_KhBc8dqmLNs04gLGtsTnAa</image>
    </theme>
    <theme id="Amazed Navbars">
        <author>Steven Sawyer (Archangel)</author>
        <link>https://play.google.com/store/apps/details?id=com.amazed.navbars</link>
        <package>com.amazed.navbars</package>
        <pricing>Paid</pricing>
        <support>overlays</support>
        <backgroundimage>https://raw.githubusercontent.com/substratum/database/master/images/amazednavbars.jpg</backgroundimage>
        <image>https://lh3.googleusercontent.com/ZUgd2pWm8rfnArzc5R4BpHQ3a07NfX4NJGrDd-6Xz2OzdL4g2Rkr_qMiR6r5nFGaREw=w300-rw</image>
    </theme>
    <theme id="AIO // THEME EXPANDER">
        <author>moelle</author>
        <link>https://play.google.com/store/apps/details?id=com.moelle.ddboot</link>
        <package>com.moelle.ddboot</package>
        <pricing>Free</pricing>
        <support>overlays|fonts|sounds|bootanimations|wallpapers</support>
        <backgroundimage>https://raw.githubusercontent.com/substratum/database/master/images/aio.png</backgroundimage>
        <image>https://lh3.googleusercontent.com/Yf5z54Rwd6kG9Mz0FBrgkLgneLjHPFHfg4DUqu78Y6-Yn8ef2mKUPD2Qzwriy16lMw=w300-rw</image>
    </theme>
    <theme id="Battery Icon Mod Substratum">
        <author>Piere R</author>
        <link>https://play.google.com/store/apps/details?id=com.pierx.baterai</link>
        <package>com.pierx.baterai</package>
        <pricing>Paid</pricing>
        <support>overlays</support>
        <backgroundimage>https://raw.githubusercontent.com/substratum/database/master/images/batteryiconmodsubstratum.jpg</backgroundimage>
        <image>https://lh3.googleusercontent.com/MtqkqqG6_e89Mks9pof11xkNcaL4Otb_AAlTHZOix4mk9PjxgFLSWDRq5zGUsqppEpo=w300-rw</image>
    </theme>
    <theme id="Boot for Subs">
        <author>Sreerag Ag</author>
        <link>https://play.google.com/store/apps/details?id=com.sreerag.boot</link>
        <package>com.sreerag.boot</package>
        <pricing>Free</pricing>
        <support>bootanimations</support>
        <backgroundimage>https://raw.githubusercontent.com/substratum/database/master/images/bootforsubs.jpg</backgroundimage>
        <image>https://lh3.googleusercontent.com/U1lBPeTNoxENSUpIuyFGJ6BLXa2bBcoWO7nIwaLiG9jGLyXYgSH3JHvPzBuAzwB1-zKi=w300-rw</image>
    </theme>
    <theme id="Curve">
        <author>Gaurav Singh</author>
        <link>https://play.google.com/store/apps/details?id=com.gaurav.curve</link>
        <package>com.gaurav.curve</package>
        <pricing>Free</pricing>
        <support>overlays</support>
        <backgroundimage>https://raw.githubusercontent.com/substratum/database/master/images/curve.png</backgroundimage>
        <image>https://lh3.googleusercontent.com/IdmC9FbXvPL-AN6zTAhwiQShr_L72rz5lF-m6tV5OuLbcQSFJZG8EFRCIdGE0zAvNr8=w300-rw</image>
    </theme>
    <theme id="Ewhats Color">
        <author>Eduardo Saiz Perez</author>
        <link>https://play.google.com/store/apps/details?id=com.dudu.EWhatsthemelite</link>
        <package>com.dudu.EWhatsthemelite</package>
        <pricing>Free</pricing>
        <support>overlays</support>
        <backgroundimage>https://raw.githubusercontent.com/substratum/database/master/images/ewhatscolor.png</backgroundimage>
        <image>http://lh3.googleusercontent.com/Q4JovgW3WTT1IIjdzPypp8Cdvxsl27TuGdHv_mZUOCGxj7eagZ4mIsQu7wck9mC8gDc=w300-rw</image>
    </theme>
    <theme id="Ewhats Theme">
        <author>Eduardo Saiz Perez</author>
        <link>https://play.google.com/store/apps/details?id=com.dudu.EWhatstheme</link>
        <package>com.dudu.EWhatstheme</package>
        <pricing>Paid</pricing>
        <support>overlays</support>
        <backgroundimage>https://raw.githubusercontent.com/substratum/database/master/images/ewhatstheme.png</backgroundimage>
        <image>http://lh3.googleusercontent.com/xANOl7M3u3vfYzQxLRupY1eyD7Qxp4gjqoyP9hBz113UYY29y6oqX15gFAn4DcvgD1I=w300-rw</image>
    </theme>
    <theme id="gaia">
        <author>De Jan (llevo3)</author>
        <link>https://play.google.com/store/apps/details?id=dejan.llevo3.gaia</link>
        <package>dejan.llevo3.gaia</package>
        <pricing>Paid</pricing>
        <support>overlays</support>
        <backgroundimage>https://raw.githubusercontent.com/substratum/database/master/images/gaia.png</backgroundimage>
        <image>https://lh3.googleusercontent.com/UpNkgD4t5ALm54C-4mlamLxgJ_nZLy2EjPlgOcNGyqg4VAPzQ6EBe9WCsMIeWlASgg=w300-rw</image>
    </theme>
    <theme id="Lock Clean">
        <author>Andre Zimmermann (Kohlewrrk)</author>
        <link>https://play.google.com/store/apps/details?id=com.kohlewrrk.lockclean</link>
        <package>com.kohlewrrk.lockclean</package>
        <pricing>Free</pricing>
        <support>overlays</support>
        <backgroundimage>https://raw.githubusercontent.com/substratum/database/master/images/lockclean.png</backgroundimage>
        <image>https://lh3.googleusercontent.com/sdH75qL7AqCR7TAdPn1vImUnr30VRy7u2zW_6SZ04CJCK4KtFZrHuHCZXEqPjFetEw=w300-rw</image>
    </theme>
    <theme id="NavBars Theme">
        <author>Faiyaz Sheth</author>
        <link>https://play.google.com/store/apps/details?id=n.n.Navbars</link>
        <package>n.n.Navbars</package>
        <pricing>Free</pricing>
        <support>overlays</support>
        <backgroundimage>https://raw.githubusercontent.com/substratum/database/master/images/navbars.png</backgroundimage>
        <image>http://lh3.googleusercontent.com/yKZr3hj1Zx8d62ANPmPgiO-OQgMacWz23ghESeYa5a_TCXc4RroLLlV7SV7H39cFtjiB=w300-rw</image>
    </theme>
    <theme id="NavSwag">
        <author>Rahul K Dinesh</author>
        <link>https://play.google.com/store/apps/details?id=com.b16h22.navswag</link>
        <package>com.b16h22.navswag</package>
        <pricing>Paid</pricing>
        <support>overlays</support>
        <backgroundimage>https://raw.githubusercontent.com/substratum/database/master/images/navswag.jpg</backgroundimage>
        <image>https://lh3.googleusercontent.com/R2aaFGSISP24Xb5RRoXXInFliUfz3rjweaDSXn1m48sFRNOJ6w86K20ZmyhmxcUVug=w300-rw</image>
    </theme>
    <theme id="Ozone">
        <author>ungeeked</author>
        <link>https://play.google.com/store/apps/details?id=com.ungeeked.ozone</link>
        <package>com.ungeeked.ozone</package>
        <pricing>Free</pricing>
        <support>overlays</support>
        <backgroundimage>https://raw.githubusercontent.com/substratum/database/master/images/ozone.png</backgroundimage>
        <image>https://lh3.googleusercontent.com/pG0-SpAT0uloqNDCSa5a2aIxXcd5QoJfsTfeZuu1SKtSG-vCYekebFjWyB6-If6_RI4=w300-rw</image>
    </theme>
    <theme id="S8 Navbar">
        <author>Orpheusdroid</author>
        <link>https://play.google.com/store/apps/details?id=com.orpheusdroid.s8navbarsubs</link>
        <package>com.orpheusdroid.s8navbarsubs</package>
        <pricing>Paid</pricing>
        <support>overlays</support>
        <backgroundimage>https://raw.githubusercontent.com/substratum/database/master/images/s8navbar.jpg</backgroundimage>
        <image>https://lh3.googleusercontent.com/tgCfhD0aKo2fWJ6KgEOPobg6U_VCLQW3xnWzMSY3cim5ivv5lKF1tteu87N0oVilbFw=w300-rw</image>
    </theme>
    <theme id="SubNa">
        <author>LF.PRODEV</author>
        <link>https://play.google.com/store/apps/details?id=lfprodev.substratum.subna</link>
        <package>lfprodev.substratum.subna</package>
        <pricing>Free</pricing>
        <support>overlays</support>
        <backgroundimage>https://raw.githubusercontent.com/substratum/database/master/images/subna.jpg</backgroundimage>
        <image>https://lh3.googleusercontent.com/tgCfhD0aKo2fWJ6KgEOPobg6U_VCLQW3xnWzMSY3cim5ivv5lKF1tteu87N0oVilbFw=w300-rw</image>
    </theme>
    <theme id="Trip Nav Bar">
        <author>Gianluca Spadazzi</author>
        <link>https://play.google.com/store/apps/details?id=com.spada.tripnavbar</link>
        <package>com.spada.tripnavbar</package>
        <pricing>Free</pricing>
        <support>overlays</support>
        <backgroundimage>https://raw.githubusercontent.com/substratum/database/master/images/tripnavbar.jpg</backgroundimage>
        <image>http://lh3.googleusercontent.com/hVi3lsMSl29sysQbIRsVQjjsCFAxy_JEEphml197mlrFZPVL-KA78qgQsQSEaBMLIPU=w300-rw</image>
    </theme>
    <theme id="Vivid Navbars Quicksettings">
        <author>Michele Amendolagine</author>
        <link>https://play.google.com/store/apps/details?id=com.ami.vivid</link>
        <package>com.ami.vivid</package>
        <pricing>Free</pricing>
        <support>overlays</support>
        <backgroundimage>https://raw.githubusercontent.com/substratum/database/master/images/vividnavbarsqs.png</backgroundimage>
        <image>https://lh3.googleusercontent.com/-d1pAUmILN1Dk9sL-KMiVUYMOliD3JBi-217FXmYXoo4fP-FCkyQSF4H_i9lePzpV8g=w300-rw</image>
    </theme>
    <theme id="Vivid Navbars Quicksettings Pro">
        <author>Michele Amendolagine</author>
        <link>https://play.google.com/store/apps/details?id=com.ami.vividiconset</link>
        <package>com.ami.vividiconset</package>
        <pricing>Paid</pricing>
        <support>overlays</support>
        <backgroundimage>https://raw.githubusercontent.com/substratum/database/master/images/vividnavbarsqspro.png</backgroundimage>
        <image>https://lh3.googleusercontent.com/fgvu0YgNdaRpYzcgKzprSmvvQ5QGaeh0Aq2EJ9W9ZvjdH8-vTJcbwTB_MndGXPXOoQ=w300-rw</image>
    </theme>
</substratum>
